odoo10_addon_l10n_es_account_balance_report-10.0.1.0.0-py2.7-nspkg.pth
odoo/addons/l10n_es_account_balance_report/__manifest__.py
odoo/addons/l10n_es_account_balance_report/__init__.py
odoo/addons/l10n_es_account_balance_report/README.rst
odoo/addons/l10n_es_account_balance_report/i18n/es.po
odoo/addons/l10n_es_account_balance_report/i18n/gl.po
odoo/addons/l10n_es_account_balance_report/i18n/ca.po
odoo/addons/l10n_es_account_balance_report/i18n/eu.po
odoo/addons/l10n_es_account_balance_report/i18n/l10n_es_account_balance_report.pot
odoo/addons/l10n_es_account_balance_report/data/estado_ingresos_gastos_normal.xml
odoo/addons/l10n_es_account_balance_report/data/pyg_abreviado.xml
odoo/addons/l10n_es_account_balance_report/data/balance_normal.xml
odoo/addons/l10n_es_account_balance_report/data/balance_pymes.xml
odoo/addons/l10n_es_account_balance_report/data/balance_abreviado.xml
odoo/addons/l10n_es_account_balance_report/data/pyg_pymes.xml
odoo/addons/l10n_es_account_balance_report/data/pyg_normal.xml
odoo/addons/l10n_es_account_balance_report/static/description/icon.png
odoo10_addon_l10n_es_account_balance_report-10.0.1.0.0.dist-info/top_level.txt
odoo10_addon_l10n_es_account_balance_report-10.0.1.0.0.dist-info/WHEEL
odoo10_addon_l10n_es_account_balance_report-10.0.1.0.0.dist-info/RECORD
odoo10_addon_l10n_es_account_balance_report-10.0.1.0.0.dist-info/metadata.json
odoo10_addon_l10n_es_account_balance_report-10.0.1.0.0.dist-info/DESCRIPTION.rst
odoo10_addon_l10n_es_account_balance_report-10.0.1.0.0.dist-info/METADATA
odoo10_addon_l10n_es_account_balance_report-10.0.1.0.0.dist-info/namespace_packages.txt
